AUTHORS
CHANGES.rst
LICENSE.rst
README.rst
pyproject.toml
setup.py
src/borghash/HashTable.c
src/borghash/HashTable.pxd
src/borghash/HashTable.pyx
src/borghash/HashTableNT.c
src/borghash/HashTableNT.pxd
src/borghash/HashTableNT.pyx
src/borghash/__init__.pxd
src/borghash/__init__.py
src/borghash/__main__.py
src/borghash.egg-info/PKG-INFO
src/borghash.egg-info/SOURCES.txt
src/borghash.egg-info/dependency_links.txt
src/borghash.egg-info/entry_points.txt
src/borghash.egg-info/top_level.txt